lookatme/contrib/qrcode.py
lookatme.contrib.qrcode-2.1.0.dist-info/LICENSE
lookatme.contrib.qrcode-2.1.0.dist-info/METADATA
lookatme.contrib.qrcode-2.1.0.dist-info/WHEEL
lookatme.contrib.qrcode-2.1.0.dist-info/top_level.txt
lookatme.contrib.qrcode-2.1.0.dist-info/RECORD
