Metadata-Version: 2.1
Name: lookatme.contrib.qrcode
Version: 2.1.0
Summary: Adds qrcode rendering
Home-page: https://github.com/d0c-s4vage/lookatme.contrib.qrcode
Author: James Johnson
Author-email: d0c.s4vage@gmail.com
License: UNKNOWN
Platform: UNKNOWN
Classifier: Environment :: Console
Classifier: Environment :: Plugins
Classifier: Intended Audience :: Developers
Classifier: License :: OSI Approved :: MIT License
Classifier: Operating System :: OS Independent
Classifier: Programming Language :: Python :: 3
Classifier: Programming Language :: Python :: 3 :: Only
Classifier: Topic :: Multimedia :: Graphics :: Presentation
Classifier: Topic :: Software Development :: Documentation
Requires-Python: >=3.6
Requires-Dist: lookatme (>=2.0.0)
Requires-Dist: PyQRCode (<2,>=1)
